{
  "conto": {
    "numero": 37183998,
    "nome": "ANDREA CHERUBINI",
    "broker": "RoboForex Ltd",
    "valuta": "EUR",
    "saldo": 111535.26,
    "equity": 111526.96,
    "margine": 10.61,
    "margine_libero": 111516.35,
    "leva": 1000,
    "profitto_giornaliero": 59.32,
    "profitto_mensile": 2129.54
  },
  "operazioni_attive": [
    {
      "simbolo": "EURUSD",
      "tipo": "SELL",
      "lotto": 0.03,
      "prezzo_apertura": 1.16635,
      "prezzo_corrente": 1.16788,
      "profitto": -4.26,
      "magic": 555,
      "commento": "Genisys ONE FX Scalping"
    },
    {
      "simbolo": "GBPUSD",
      "tipo": "SELL",
      "lotto": 0.02,
      "prezzo_apertura": 1.34338,
      "prezzo_corrente": 1.34502,
      "profitto": -3.00,
      "magic": 555,
      "commento": "Genisys ONE FX Scalping"
    },
    {
      "simbolo": "EURUSD",
      "tipo": "SELL",
      "lotto": 0.03,
      "prezzo_apertura": 1.16801,
      "prezzo_corrente": 1.16788,
      "profitto": 0.00,
      "magic": 555,
      "commento": "Genisys ONE FX Martingale"
    },
    {
      "simbolo": "GBPUSD",
      "tipo": "SELL",
      "lotto": 0.02,
      "prezzo_apertura": 1.34452,
      "prezzo_corrente": 1.34502,
      "profitto": -1.04,
      "magic": 555,
      "commento": "Genisys ONE FX Martingale"
    }
  ],
  "aggiornato_il": "2025.07.15 15:57"
}