{
  "conto": {
    "numero": 37183998,
    "nome": "ANDREA CHERUBINI",
    "broker": "RoboForex Ltd",
    "valuta": "EUR",
    "saldo": 110101.57,
    "equity": 110094.01,
    "margine": 15.47,
    "margine_libero": 110078.54,
    "leva": 1000,
    "profitto_giornaliero": 42.04,
    "profitto_mensile": 683.12
  },
  "operazioni_attive": [
    {
      "simbolo": "EURUSD",
      "tipo": "BUY",
      "lotto": 0.03,
      "prezzo_apertura": 1.18099,
      "prezzo_corrente": 1.17928,
      "profitto": -4.35,
      "magic": 123,
      "commento": "Genisys ONE FX Scalping"
    },
    {
      "simbolo": "EURUSD",
      "tipo": "BUY",
      "lotto": 0.03,
      "prezzo_apertura": 1.18026,
      "prezzo_corrente": 1.17928,
      "profitto": -2.49,
      "magic": 123,
      "commento": "Genisys ONE FX Martingale"
    },
    {
      "simbolo": "EURUSD",
      "tipo": "BUY",
      "lotto": 0.04,
      "prezzo_apertura": 1.17955,
      "prezzo_corrente": 1.17928,
      "profitto": -0.92,
      "magic": 123,
      "commento": "Genisys ONE FX Martingale"
    },
    {
      "simbolo": "EURUSD",
      "tipo": "BUY",
      "lotto": 0.05,
      "prezzo_apertura": 1.17884,
      "prezzo_corrente": 1.17928,
      "profitto": 1.87,
      "magic": 123,
      "commento": "Genisys ONE FX Martingale"
    },
    {
      "simbolo": "EURUSD",
      "tipo": "SELL",
      "lotto": 0.03,
      "prezzo_apertura": 1.17884,
      "prezzo_corrente": 1.17928,
      "profitto": -1.42,
      "magic": 555,
      "commento": "Genisys ONE FX Scalping"
    },
    {
      "simbolo": "EURUSD",
      "tipo": "SELL",
      "lotto": 0.03,
      "prezzo_apertura": 1.17969,
      "prezzo_corrente": 1.17928,
      "profitto": 0.74,
      "magic": 555,
      "commento": "Genisys ONE FX Martingale"
    },
    {
      "simbolo": "GBPUSD",
      "tipo": "BUY",
      "lotto": 0.02,
      "prezzo_apertura": 1.36659,
      "prezzo_corrente": 1.36606,
      "profitto": -0.90,
      "magic": 123,
      "commento": "Genisys ONE FX Scalping"
    },
    {
      "simbolo": "GBPUSD",
      "tipo": "BUY",
      "lotto": 0.02,
      "prezzo_apertura": 1.36578,
      "prezzo_corrente": 1.36606,
      "profitto": 0.47,
      "magic": 123,
      "commento": "Genisys ONE FX Martingale"
    },
    {
      "simbolo": "GBPUSD",
      "tipo": "SELL",
      "lotto": 0.02,
      "prezzo_apertura": 1.36584,
      "prezzo_corrente": 1.36606,
      "profitto": -0.56,
      "magic": 555,
      "commento": "Genisys ONE FX Scalping"
    }
  ],
  "aggiornato_il": "2025.07.03 14:44"
}