{
  "conto": {
    "numero": 37183998,
    "nome": "ANDREA CHERUBINI",
    "broker": "RoboForex Ltd",
    "valuta": "EUR",
    "saldo": 109390.17,
    "equity": 109384.96,
    "margine": 8.33,
    "margine_libero": 109376.63,
    "leva": 1000,
    "profitto_giornaliero": 130.27,
    "profitto_mensile": 4409.96
  },
  "operazioni_attive": [
    {
      "simbolo": "GBPUSD",
      "tipo": "SELL",
      "lotto": 0.02,
      "prezzo_apertura": 1.36938,
      "prezzo_corrente": 1.37008,
      "profitto": -1.40,
      "magic": 555,
      "commento": "Genisys ONE FX Scalping"
    },
    {
      "simbolo": "GBPUSD",
      "tipo": "SELL",
      "lotto": 0.02,
      "prezzo_apertura": 1.37057,
      "prezzo_corrente": 1.37008,
      "profitto": 0.63,
      "magic": 555,
      "commento": "Genisys ONE FX Martingale"
    },
    {
      "simbolo": "GBPUSD",
      "tipo": "BUY",
      "lotto": 0.02,
      "prezzo_apertura": 1.37105,
      "prezzo_corrente": 1.37008,
      "profitto": -1.65,
      "magic": 123,
      "commento": "Genisys ONE FX Scalping"
    },
    {
      "simbolo": "EURUSD",
      "tipo": "BUY",
      "lotto": 0.03,
      "prezzo_apertura": 1.17520,
      "prezzo_corrente": 1.17434,
      "profitto": -2.20,
      "magic": 123,
      "commento": "Genisys ONE FX Scalping"
    },
    {
      "simbolo": "EURUSD",
      "tipo": "BUY",
      "lotto": 0.03,
      "prezzo_apertura": 1.17447,
      "prezzo_corrente": 1.17434,
      "profitto": -0.33,
      "magic": 123,
      "commento": "Genisys ONE FX Martingale"
    },
    {
      "simbolo": "GBPUSD",
      "tipo": "BUY",
      "lotto": 0.02,
      "prezzo_apertura": 1.37023,
      "prezzo_corrente": 1.37008,
      "profitto": -0.26,
      "magic": 123,
      "commento": "Genisys ONE FX Martingale"
    }
  ],
  "aggiornato_il": "2025.06.30 18:41"
}