{
  "conto": {
    "numero": 37183998,
    "nome": "ANDREA CHERUBINI",
    "broker": "RoboForex Ltd",
    "valuta": "EUR",
    "saldo": 108255.36,
    "equity": 108221.98,
    "margine": 35.37,
    "margine_libero": 108186.61,
    "leva": 1000,
    "profitto_giornaliero": 25.79,
    "profitto_mensile": 3267.87
  },
  "operazioni_attive": [
    {
      "simbolo": "EURUSD",
      "tipo": "BUY",
      "lotto": 0.03,
      "prezzo_apertura": 1.16293,
      "prezzo_corrente": 1.15955,
      "profitto": -8.74,
      "magic": 123,
      "commento": "Genisys ONE FX Scalping"
    },
    {
      "simbolo": "EURUSD",
      "tipo": "BUY",
      "lotto": 0.03,
      "prezzo_apertura": 1.16220,
      "prezzo_corrente": 1.15955,
      "profitto": -6.86,
      "magic": 123,
      "commento": "Genisys ONE FX Martingale"
    },
    {
      "simbolo": "EURUSD",
      "tipo": "BUY",
      "lotto": 0.04,
      "prezzo_apertura": 1.16148,
      "prezzo_corrente": 1.15955,
      "profitto": -6.66,
      "magic": 123,
      "commento": "Genisys ONE FX Martingale"
    },
    {
      "simbolo": "EURUSD",
      "tipo": "BUY",
      "lotto": 0.05,
      "prezzo_apertura": 1.16079,
      "prezzo_corrente": 1.15955,
      "profitto": -5.35,
      "magic": 123,
      "commento": "Genisys ONE FX Martingale"
    },
    {
      "simbolo": "EURUSD",
      "tipo": "BUY",
      "lotto": 0.07,
      "prezzo_apertura": 1.16009,
      "prezzo_corrente": 1.15955,
      "profitto": -3.26,
      "magic": 123,
      "commento": "Genisys ONE FX Martingale"
    },
    {
      "simbolo": "GBPUSD",
      "tipo": "BUY",
      "lotto": 0.02,
      "prezzo_apertura": 1.36306,
      "prezzo_corrente": 1.36173,
      "profitto": -2.29,
      "magic": 123,
      "commento": "Genisys ONE FX Scalping"
    },
    {
      "simbolo": "EURUSD",
      "tipo": "BUY",
      "lotto": 0.09,
      "prezzo_apertura": 1.15937,
      "prezzo_corrente": 1.15955,
      "profitto": 1.40,
      "magic": 123,
      "commento": "Genisys ONE FX Martingale"
    },
    {
      "simbolo": "EURUSD",
      "tipo": "SELL",
      "lotto": 0.03,
      "prezzo_apertura": 1.15937,
      "prezzo_corrente": 1.15955,
      "profitto": -0.80,
      "magic": 555,
      "commento": "Genisys ONE FX Scalping"
    },
    {
      "simbolo": "GBPUSD",
      "tipo": "SELL",
      "lotto": 0.02,
      "prezzo_apertura": 1.36091,
      "prezzo_corrente": 1.36173,
      "profitto": -1.62,
      "magic": 555,
      "commento": "Genisys ONE FX Scalping"
    },
    {
      "simbolo": "GBPUSD",
      "tipo": "BUY",
      "lotto": 0.02,
      "prezzo_apertura": 1.36101,
      "prezzo_corrente": 1.36173,
      "profitto": 1.24,
      "magic": 123,
      "commento": "Genisys ONE FX Martingale"
    },
    {
      "simbolo": "GBPUSD",
      "tipo": "BUY",
      "lotto": 0.03,
      "prezzo_apertura": 1.36182,
      "prezzo_corrente": 1.36173,
      "profitto": -0.23,
      "magic": 123,
      "commento": "Genisys ONE FX Martingale"
    },
    {
      "simbolo": "GBPUSD",
      "tipo": "SELL",
      "lotto": 0.02,
      "prezzo_apertura": 1.36173,
      "prezzo_corrente": 1.36173,
      "profitto": -0.21,
      "magic": 555,
      "commento": "Genisys ONE FX Martingale"
    }
  ],
  "aggiornato_il": "2025.06.25 11:21"
}