{
  "conto": {
    "numero": 37183998,
    "nome": "ANDREA CHERUBINI",
    "broker": "RoboForex Ltd",
    "valuta": "EUR",
    "saldo": 111898.44,
    "equity": 111886.18,
    "margine": 7.96,
    "margine_libero": 111878.22,
    "leva": 1000,
    "profitto_giornaliero": 332.10,
    "profitto_mensile": 2495.17
  },
  "operazioni_attive": [
    {
      "simbolo": "EURUSD",
      "tipo": "BUY",
      "lotto": 0.03,
      "prezzo_apertura": 1.16568,
      "prezzo_corrente": 1.16343,
      "profitto": -5.80,
      "magic": 123,
      "commento": "Genisys ONE FX Scalping"
    },
    {
      "simbolo": "GBPUSD",
      "tipo": "BUY",
      "lotto": 0.02,
      "prezzo_apertura": 1.34391,
      "prezzo_corrente": 1.34120,
      "profitto": -4.66,
      "magic": 123,
      "commento": "Genisys ONE FX Scalping"
    },
    {
      "simbolo": "GBPUSD",
      "tipo": "SELL",
      "lotto": 0.02,
      "prezzo_apertura": 1.34145,
      "prezzo_corrente": 1.34120,
      "profitto": 0.21,
      "magic": 555,
      "commento": "Genisys ONE FX Scalping"
    },
    {
      "simbolo": "EURUSD",
      "tipo": "BUY",
      "lotto": 0.03,
      "prezzo_apertura": 1.16380,
      "prezzo_corrente": 1.16343,
      "profitto": -0.95,
      "magic": 123,
      "commento": "Genisys ONE FX Martingale"
    },
    {
      "simbolo": "GBPUSD",
      "tipo": "BUY",
      "lotto": 0.02,
      "prezzo_apertura": 1.34158,
      "prezzo_corrente": 1.34120,
      "profitto": -0.65,
      "magic": 123,
      "commento": "Genisys ONE FX Martingale"
    },
    {
      "simbolo": "EURUSD",
      "tipo": "SELL",
      "lotto": 0.03,
      "prezzo_apertura": 1.16340,
      "prezzo_corrente": 1.16343,
      "profitto": -0.41,
      "magic": 555,
      "commento": "Genisys ONE FX Scalping"
    }
  ],
  "aggiornato_il": "2025.07.16 21:42"
}