{
  "conto": {
    "numero": 37183998,
    "nome": "ANDREA CHERUBINI",
    "broker": "RoboForex Ltd",
    "valuta": "EUR",
    "saldo": 111481.76,
    "equity": 111431.00,
    "margine": 62.28,
    "margine_libero": 111368.72,
    "leva": 1000,
    "profitto_giornaliero": 2.62,
    "profitto_mensile": 2072.84
  },
  "operazioni_attive": [
    {
      "simbolo": "GBPUSD",
      "tipo": "BUY",
      "lotto": 0.02,
      "prezzo_apertura": 1.34933,
      "prezzo_corrente": 1.34374,
      "profitto": -9.58,
      "magic": 123,
      "commento": "Genisys ONE FX Scalping"
    },
    {
      "simbolo": "GBPUSD",
      "tipo": "BUY",
      "lotto": 0.02,
      "prezzo_apertura": 1.34843,
      "prezzo_corrente": 1.34374,
      "profitto": -8.04,
      "magic": 123,
      "commento": "Genisys ONE FX Martingale"
    },
    {
      "simbolo": "GBPUSD",
      "tipo": "BUY",
      "lotto": 0.03,
      "prezzo_apertura": 1.34762,
      "prezzo_corrente": 1.34374,
      "profitto": -9.97,
      "magic": 123,
      "commento": "Genisys ONE FX Martingale"
    },
    {
      "simbolo": "GBPUSD",
      "tipo": "BUY",
      "lotto": 0.03,
      "prezzo_apertura": 1.34681,
      "prezzo_corrente": 1.34374,
      "profitto": -7.89,
      "magic": 123,
      "commento": "Genisys ONE FX Martingale"
    },
    {
      "simbolo": "GBPUSD",
      "tipo": "BUY",
      "lotto": 0.04,
      "prezzo_apertura": 1.34599,
      "prezzo_corrente": 1.34374,
      "profitto": -7.71,
      "magic": 123,
      "commento": "Genisys ONE FX Martingale"
    },
    {
      "simbolo": "GBPUSD",
      "tipo": "BUY",
      "lotto": 0.06,
      "prezzo_apertura": 1.34518,
      "prezzo_corrente": 1.34374,
      "profitto": -7.40,
      "magic": 123,
      "commento": "Genisys ONE FX Martingale"
    },
    {
      "simbolo": "GBPUSD",
      "tipo": "BUY",
      "lotto": 0.07,
      "prezzo_apertura": 1.34434,
      "prezzo_corrente": 1.34374,
      "profitto": -3.60,
      "magic": 123,
      "commento": "Genisys ONE FX Martingale"
    },
    {
      "simbolo": "EURUSD",
      "tipo": "BUY",
      "lotto": 0.03,
      "prezzo_apertura": 1.16952,
      "prezzo_corrente": 1.16719,
      "profitto": -5.99,
      "magic": 123,
      "commento": "Genisys ONE FX Scalping"
    },
    {
      "simbolo": "GBPUSD",
      "tipo": "BUY",
      "lotto": 0.10,
      "prezzo_apertura": 1.34352,
      "prezzo_corrente": 1.34374,
      "profitto": 1.88,
      "magic": 123,
      "commento": "Genisys ONE FX Martingale"
    },
    {
      "simbolo": "EURUSD",
      "tipo": "BUY",
      "lotto": 0.03,
      "prezzo_apertura": 1.16712,
      "prezzo_corrente": 1.16719,
      "profitto": 0.18,
      "magic": 123,
      "commento": "Genisys ONE FX Martingale"
    },
    {
      "simbolo": "EURUSD",
      "tipo": "BUY",
      "lotto": 0.04,
      "prezzo_apertura": 1.16638,
      "prezzo_corrente": 1.16719,
      "profitto": 2.78,
      "magic": 123,
      "commento": "Genisys ONE FX Martingale"
    },
    {
      "simbolo": "GBPUSD",
      "tipo": "BUY",
      "lotto": 0.13,
      "prezzo_apertura": 1.34272,
      "prezzo_corrente": 1.34374,
      "profitto": 11.36,
      "magic": 123,
      "commento": "Genisys ONE FX Martingale"
    },
    {
      "simbolo": "EURUSD",
      "tipo": "SELL",
      "lotto": 0.03,
      "prezzo_apertura": 1.16663,
      "prezzo_corrente": 1.16719,
      "profitto": -1.80,
      "magic": 555,
      "commento": "Genisys ONE FX Scalping"
    },
    {
      "simbolo": "GBPUSD",
      "tipo": "SELL",
      "lotto": 0.02,
      "prezzo_apertura": 1.34292,
      "prezzo_corrente": 1.34374,
      "profitto": -1.61,
      "magic": 555,
      "commento": "Genisys ONE FX Scalping"
    },
    {
      "simbolo": "GBPUSD",
      "tipo": "SELL",
      "lotto": 0.02,
      "prezzo_apertura": 1.34373,
      "prezzo_corrente": 1.34374,
      "profitto": -0.22,
      "magic": 555,
      "commento": "Genisys ONE FX Martingale"
    },
    {
      "simbolo": "EURUSD",
      "tipo": "SELL",
      "lotto": 0.03,
      "prezzo_apertura": 1.16735,
      "prezzo_corrente": 1.16719,
      "profitto": 0.05,
      "magic": 555,
      "commento": "Genisys ONE FX Martingale"
    }
  ],
  "aggiornato_il": "2025.07.15 04:54"
}