{
  "conto": {
    "numero": 37183998,
    "nome": "ANDREA CHERUBINI",
    "broker": "RoboForex Ltd",
    "valuta": "EUR",
    "saldo": 108249.13,
    "equity": 108234.06,
    "margine": 19.69,
    "margine_libero": 108214.37,
    "leva": 1000,
    "profitto_giornaliero": 19.56,
    "profitto_mensile": 3261.64
  },
  "operazioni_attive": [
    {
      "simbolo": "EURUSD",
      "tipo": "BUY",
      "lotto": 0.03,
      "prezzo_apertura": 1.16293,
      "prezzo_corrente": 1.16053,
      "profitto": -6.20,
      "magic": 123,
      "commento": "Genisys ONE FX Scalping"
    },
    {
      "simbolo": "EURUSD",
      "tipo": "BUY",
      "lotto": 0.03,
      "prezzo_apertura": 1.16220,
      "prezzo_corrente": 1.16053,
      "profitto": -4.32,
      "magic": 123,
      "commento": "Genisys ONE FX Martingale"
    },
    {
      "simbolo": "EURUSD",
      "tipo": "BUY",
      "lotto": 0.04,
      "prezzo_apertura": 1.16148,
      "prezzo_corrente": 1.16053,
      "profitto": -3.27,
      "magic": 123,
      "commento": "Genisys ONE FX Martingale"
    },
    {
      "simbolo": "GBPUSD",
      "tipo": "BUY",
      "lotto": 0.02,
      "prezzo_apertura": 1.36260,
      "prezzo_corrente": 1.36215,
      "profitto": -0.78,
      "magic": 123,
      "commento": "Genisys ONE FX Scalping"
    },
    {
      "simbolo": "EURUSD",
      "tipo": "BUY",
      "lotto": 0.05,
      "prezzo_apertura": 1.16079,
      "prezzo_corrente": 1.16053,
      "profitto": -1.12,
      "magic": 123,
      "commento": "Genisys ONE FX Martingale"
    },
    {
      "simbolo": "GBPUSD",
      "tipo": "BUY",
      "lotto": 0.02,
      "prezzo_apertura": 1.36179,
      "prezzo_corrente": 1.36215,
      "profitto": 0.62,
      "magic": 123,
      "commento": "Genisys ONE FX Martingale"
    }
  ],
  "aggiornato_il": "2025.06.25 09:58"
}