{
  "conto": {
    "numero": 37183998,
    "nome": "ANDREA CHERUBINI",
    "broker": "RoboForex Ltd",
    "valuta": "EUR",
    "saldo": 112726.99,
    "equity": 112646.04,
    "margine": 86.70,
    "margine_libero": 112559.34,
    "leva": 1000,
    "profitto_giornaliero": 15.18,
    "profitto_mensile": 3350.83
  },
  "operazioni_attive": [
    {
      "simbolo": "GBPUSD",
      "tipo": "BUY",
      "lotto": 0.02,
      "prezzo_apertura": 1.35622,
      "prezzo_corrente": 1.34914,
      "profitto": -12.05,
      "magic": 123,
      "commento": "Genisys ONE FX Scalping"
    },
    {
      "simbolo": "GBPUSD",
      "tipo": "BUY",
      "lotto": 0.02,
      "prezzo_apertura": 1.35408,
      "prezzo_corrente": 1.34914,
      "profitto": -8.41,
      "magic": 123,
      "commento": "Genisys ONE FX Martingale"
    },
    {
      "simbolo": "GBPUSD",
      "tipo": "BUY",
      "lotto": 0.03,
      "prezzo_apertura": 1.35488,
      "prezzo_corrente": 1.34914,
      "profitto": -14.65,
      "magic": 123,
      "commento": "Genisys ONE FX Martingale"
    },
    {
      "simbolo": "GBPUSD",
      "tipo": "BUY",
      "lotto": 0.03,
      "prezzo_apertura": 1.35323,
      "prezzo_corrente": 1.34914,
      "profitto": -10.44,
      "magic": 123,
      "commento": "Genisys ONE FX Martingale"
    },
    {
      "simbolo": "GBPUSD",
      "tipo": "BUY",
      "lotto": 0.04,
      "prezzo_apertura": 1.35241,
      "prezzo_corrente": 1.34914,
      "profitto": -11.13,
      "magic": 123,
      "commento": "Genisys ONE FX Martingale"
    },
    {
      "simbolo": "GBPUSD",
      "tipo": "BUY",
      "lotto": 0.06,
      "prezzo_apertura": 1.35160,
      "prezzo_corrente": 1.34914,
      "profitto": -12.56,
      "magic": 123,
      "commento": "Genisys ONE FX Martingale"
    },
    {
      "simbolo": "GBPUSD",
      "tipo": "BUY",
      "lotto": 0.07,
      "prezzo_apertura": 1.35079,
      "prezzo_corrente": 1.34914,
      "profitto": -9.83,
      "magic": 123,
      "commento": "Genisys ONE FX Martingale"
    },
    {
      "simbolo": "GBPUSD",
      "tipo": "BUY",
      "lotto": 0.10,
      "prezzo_apertura": 1.34998,
      "prezzo_corrente": 1.34914,
      "profitto": -7.15,
      "magic": 123,
      "commento": "Genisys ONE FX Martingale"
    },
    {
      "simbolo": "GBPUSD",
      "tipo": "BUY",
      "lotto": 0.13,
      "prezzo_apertura": 1.34914,
      "prezzo_corrente": 1.34914,
      "profitto": 0.00,
      "magic": 123,
      "commento": "Genisys ONE FX Martingale"
    },
    {
      "simbolo": "EURUSD",
      "tipo": "SELL",
      "lotto": 0.03,
      "prezzo_apertura": 1.17379,
      "prezzo_corrente": 1.17509,
      "profitto": -3.62,
      "magic": 555,
      "commento": "Genisys ONE FX Scalping"
    },
    {
      "simbolo": "EURUSD",
      "tipo": "SELL",
      "lotto": 0.03,
      "prezzo_apertura": 1.17449,
      "prezzo_corrente": 1.17509,
      "profitto": -1.84,
      "magic": 555,
      "commento": "Genisys ONE FX Martingale"
    },
    {
      "simbolo": "GBPUSD",
      "tipo": "BUY",
      "lotto": 0.16,
      "prezzo_apertura": 1.34831,
      "prezzo_corrente": 1.34914,
      "profitto": 11.30,
      "magic": 123,
      "commento": "Genisys ONE FX Martingale"
    },
    {
      "simbolo": "EURUSD",
      "tipo": "SELL",
      "lotto": 0.04,
      "prezzo_apertura": 1.17519,
      "prezzo_corrente": 1.17509,
      "profitto": -0.07,
      "magic": 555,
      "commento": "Genisys ONE FX Martingale"
    },
    {
      "simbolo": "EURUSD",
      "tipo": "BUY",
      "lotto": 0.03,
      "prezzo_apertura": 1.17576,
      "prezzo_corrente": 1.17509,
      "profitto": -1.71,
      "magic": 123,
      "commento": "Genisys ONE FX Scalping"
    },
    {
      "simbolo": "EURUSD",
      "tipo": "SELL",
      "lotto": 0.05,
      "prezzo_apertura": 1.17592,
      "prezzo_corrente": 1.17509,
      "profitto": 3.02,
      "magic": 555,
      "commento": "Genisys ONE FX Martingale"
    },
    {
      "simbolo": "GBPUSD",
      "tipo": "SELL",
      "lotto": 0.02,
      "prezzo_apertura": 1.34883,
      "prezzo_corrente": 1.34914,
      "profitto": -0.71,
      "magic": 555,
      "commento": "Genisys ONE FX Scalping"
    },
    {
      "simbolo": "EURUSD",
      "tipo": "BUY",
      "lotto": 0.03,
      "prezzo_apertura": 1.17504,
      "prezzo_corrente": 1.17509,
      "profitto": 0.13,
      "magic": 123,
      "commento": "Genisys ONE FX Martingale"
    }
  ],
  "aggiornato_il": "2025.07.25 10:02"
}