{
  "conto": {
    "numero": 76675479,
    "nome": "11098900",
    "broker": "Ava Trade EU Ltd.",
    "valuta": "EUR",
    "saldo": 6390.69,
    "equity": 6271.28,
    "margine": 691.22,
    "margine_libero": 5580.06,
    "leva": 400,
    "profitto_giornaliero": 0.00,
    "profitto_mensile": 2.56
  },
  "operazioni_attive": [
    {
      "simbolo": "USDCAD",
      "tipo": "SELL",
      "lotto": 0.02,
      "prezzo_apertura": 1.37867,
      "prezzo_corrente": 1.37995,
      "profitto": -1.81,
      "magic": 555,
      "commento": "0"
    },
    {
      "simbolo": "USDCAD",
      "tipo": "SELL",
      "lotto": 0.02,
      "prezzo_apertura": 1.37267,
      "prezzo_corrente": 1.37995,
      "profitto": -9.27,
      "magic": 555,
      "commento": "0"
    },
    {
      "simbolo": "USDCAD",
      "tipo": "BUY",
      "lotto": 0.03,
      "prezzo_apertura": 1.37356,
      "prezzo_corrente": 1.37995,
      "profitto": 11.92,
      "magic": 123,
      "commento": "0"
    },
    {
      "simbolo": "USDCAD",
      "tipo": "BUY",
      "lotto": 0.02,
      "prezzo_apertura": 1.37955,
      "prezzo_corrente": 1.37995,
      "profitto": 0.50,
      "magic": 123,
      "commento": "0"
    },
    {
      "simbolo": "USDCAD",
      "tipo": "BUY",
      "lotto": 0.02,
      "prezzo_apertura": 1.38555,
      "prezzo_corrente": 1.37995,
      "profitto": -6.96,
      "magic": 123,
      "commento": "0"
    },
    {
      "simbolo": "USDCAD",
      "tipo": "BUY",
      "lotto": 0.02,
      "prezzo_apertura": 1.39159,
      "prezzo_corrente": 1.37995,
      "profitto": -14.47,
      "magic": 123,
      "commento": "0"
    },
    {
      "simbolo": "EURUSD",
      "tipo": "BUY",
      "lotto": 0.02,
      "prezzo_apertura": 1.16668,
      "prezzo_corrente": 1.16584,
      "profitto": -1.44,
      "magic": 123,
      "commento": "0"
    },
    {
      "simbolo": "EURUSD",
      "tipo": "BUY",
      "lotto": 0.02,
      "prezzo_apertura": 1.17261,
      "prezzo_corrente": 1.16584,
      "profitto": -11.61,
      "magic": 123,
      "commento": "0"
    },
    {
      "simbolo": "EURUSD",
      "tipo": "SELL",
      "lotto": 0.04,
      "prezzo_apertura": 1.16883,
      "prezzo_corrente": 1.16584,
      "profitto": 9.98,
      "magic": 555,
      "commento": "0"
    },
    {
      "simbolo": "EURUSD",
      "tipo": "SELL",
      "lotto": 0.03,
      "prezzo_apertura": 1.16283,
      "prezzo_corrente": 1.16584,
      "profitto": -7.95,
      "magic": 555,
      "commento": "0"
    },
    {
      "simbolo": "EURUSD",
      "tipo": "SELL",
      "lotto": 0.02,
      "prezzo_apertura": 1.15679,
      "prezzo_corrente": 1.16584,
      "profitto": -15.66,
      "magic": 555,
      "commento": "0"
    },
    {
      "simbolo": "EURUSD",
      "tipo": "SELL",
      "lotto": 0.02,
      "prezzo_apertura": 1.14628,
      "prezzo_corrente": 1.16584,
      "profitto": -33.69,
      "magic": 555,
      "commento": "0"
    },
    {
      "simbolo": "EURUSD",
      "tipo": "SELL",
      "lotto": 0.02,
      "prezzo_apertura": 1.14019,
      "prezzo_corrente": 1.16584,
      "profitto": -44.14,
      "magic": 555,
      "commento": "0"
    }
  ],
  "aggiornato_il": "2025.09.04 01:55"
}